schedule/__init__.py
schedule/py.typed
simulation_schedule-1.2.6.dist-info/AUTHORS.rst
simulation_schedule-1.2.6.dist-info/LICENSE.txt
simulation_schedule-1.2.6.dist-info/METADATA
simulation_schedule-1.2.6.dist-info/WHEEL
simulation_schedule-1.2.6.dist-info/top_level.txt
simulation_schedule-1.2.6.dist-info/RECORD
