Metadata-Version: 2.1
Name: simulation-schedule
Version: 1.2.6
Summary: Job scheduling for humans.
Home-page: https://github.com/dbader/schedule
Download-URL: https://github.com/dbader/schedule/tarball/1.2.6
Author: Daniel Bader
Author-email: mail@dbader.org
License: MIT
Keywords: schedule,periodic,jobs,scheduling,clockwork,cron,scheduler,job scheduling
Classifier: Intended Audience :: Developers
Classifier: License :: OSI Approved :: MIT License
Classifier: Development Status :: 5 - Production/Stable
Classifier: Operating System :: OS Independent
Classifier: Programming Language :: Python
Classifier: Programming Language :: Python :: 3
Classifier: Programming Language :: Python :: 3.7
Classifier: Programming Language :: Python :: 3.8
Classifier: Programming Language :: Python :: 3.9
Classifier: Programming Language :: Python :: 3.10
Classifier: Programming Language :: Python :: 3.11
Classifier: Programming Language :: Python :: 3.12
Classifier: Natural Language :: English
Requires-Python: >=3.7
License-File: LICENSE.txt
License-File: AUTHORS.rst
